LLM_keyword_extractor/__init__.py
LLM_keyword_extractor/main.py.py
LLM_keyword_extractor-0.1.dist-info/METADATA
LLM_keyword_extractor-0.1.dist-info/WHEEL
LLM_keyword_extractor-0.1.dist-info/top_level.txt
LLM_keyword_extractor-0.1.dist-info/RECORD
