Metadata-Version: 2.1
Name: LLM-keyword-extractor
Version: 0.1
Summary: This is a python package to extract keywords from a given text using LLMs
Author: Sandeep Chataut
Author-email: sandeepkesh52@gmail.com
Requires-Dist: transformers
Requires-Dist: langchain
Requires-Dist: torch
Requires-Dist: einops
Requires-Dist: accelerate
Requires-Dist: bitsandbytes
